eos.cpython-310-darwin.so
eos_py-1.5.0.dist-info/RECORD
eos_py-1.5.0.dist-info/LICENSE
eos_py-1.5.0.dist-info/WHEEL
eos_py-1.5.0.dist-info/top_level.txt
eos_py-1.5.0.dist-info/METADATA
