Metadata-Version: 2.1
Name: eos-py
Version: 1.5.0
Summary: Python bindings for eos - A lightweight 3D Morphable Face Model fitting library in modern C++11/14
Home-page: https://github.com/patrikhuber/eos
Author: Patrik Huber
Author-email: patrikhuber@gmail.com
License: Apache-2.0
Platform: UNKNOWN
License-File: LICENSE
